db_access/__init__.py
db_access/db_access.py
db_access-0.1.2.dist-info/LICENSE
db_access-0.1.2.dist-info/METADATA
db_access-0.1.2.dist-info/WHEEL
db_access-0.1.2.dist-info/top_level.txt
db_access-0.1.2.dist-info/RECORD
