Metadata-Version: 2.1
Name: db-access
Version: 0.1.2
Summary: Easy db access through sqlalchemy
Home-page: https://github.com/weiyiyin0321/easy_db_access.git
Author: Weiyi Yin
License: UNKNOWN
Platform: UNKNOWN
Classifier: Programming Language :: Python :: 3
Classifier: License :: OSI Approved :: MIT License
Classifier: Operating System :: OS Independent
Requires-Dist: cx-Oracle
Requires-Dist: pyodbc
Requires-Dist: sqlalchemy
Requires-Dist: impyla
Requires-Dist: pymysql
